vspscripts/VERSION
vspscripts/__init__.py
vspscripts/alignment/PyAlignment.py
vspscripts/alignment/PyMatch.py
vspscripts/alignment/__init__.py
vspscripts/alignment/alignment_all.py
vspscripts/alignment/setup.py
vspscripts/alignment/test.py
vspscripts/alignment/matching/__init__.py
vspscripts/alignment/matching/dist.py
vspscripts/alignment/matching/matching.py
vspscripts/alignment/tools/__init__.py
vspscripts/alignment/tools/evaluation.py
vspscripts/alignment/tools/show_imgs.py
vspscripts/alignment/tools/show_matchTemp.py
vspscripts/alignment/tools/show_pixel.py
vspscripts/alignment/utils/__init__.py
vspscripts/alignment/utils/ann.py
vspscripts/alignment/utils/gol.py
vspscripts/alignment/utils/img.py
vspscripts/alignment/utils/mat.py
vspscripts/alignment/utils/utils.py
vspscripts/annotation/__init__.py
vspscripts/annotation/cityscapesLabelTool.py
vspscripts/annotation/icons/back.png
vspscripts/annotation/icons/checked6.png
vspscripts/annotation/icons/checked6_red.png
vspscripts/annotation/icons/clearpolygon.png
vspscripts/annotation/icons/deleteobject.png
vspscripts/annotation/icons/exit.png
vspscripts/annotation/icons/filepath.png
vspscripts/annotation/icons/help19.png
vspscripts/annotation/icons/highlight.png
vspscripts/annotation/icons/layerdown.png
vspscripts/annotation/icons/layerup.png
vspscripts/annotation/icons/minus.png
vspscripts/annotation/icons/modify.png
vspscripts/annotation/icons/newobject.png
vspscripts/annotation/icons/next.png
vspscripts/annotation/icons/open.png
vspscripts/annotation/icons/play.png
vspscripts/annotation/icons/plus.png
vspscripts/annotation/icons/save.png
vspscripts/annotation/icons/screenshot.png
vspscripts/annotation/icons/screenshotToggle.png
vspscripts/annotation/icons/shuffle.png
vspscripts/annotation/icons/undo.png
vspscripts/annotation/icons/zoom.png
vspscripts/download/__init__.py
vspscripts/download/downloader.py
vspscripts/evaluation/__init__.py
vspscripts/evaluation/evalInstanceLevelSemanticLabeling.py
vspscripts_python-1.2.2.dist-info/METADATA
vspscripts_python-1.2.2.dist-info/WHEEL
vspscripts_python-1.2.2.dist-info/entry_points.txt
vspscripts_python-1.2.2.dist-info/top_level.txt
vspscripts_python-1.2.2.dist-info/RECORD
