Metadata-Version: 2.1
Name: vspscripts-python
Version: 1.2.2
Summary: Python Scripts for the VSP Dataset
Home-page: UNKNOWN
Author: WJG
Author-email: wangjiangong2018@ia.ac.cn
License: MIT license
Platform: UNKNOWN
Requires-Dist: numpy
Requires-Dist: matplotlib
Requires-Dist: pillow
Requires-Dist: appdirs
Requires-Dist: pyquaternion
Requires-Dist: coloredlogs
Requires-Dist: tqdm
Requires-Dist: typing
Requires-Dist: scikit-learn
Provides-Extra: gui
Requires-Dist: PyQt5 ; extra == 'gui'
